nyaadl/__init__.py
nyaadl/__main__.py
nyaadl/cli.py
nyaadl/config.py
nyaadl/executor.py
nyaadl/nyaa.py
nyaadl-0.2.3.dist-info/LICENSE
nyaadl-0.2.3.dist-info/METADATA
nyaadl-0.2.3.dist-info/WHEEL
nyaadl-0.2.3.dist-info/entry_points.txt
nyaadl-0.2.3.dist-info/top_level.txt
nyaadl-0.2.3.dist-info/RECORD
