Metadata-Version: 2.1
Name: nyaadl
Version: 0.2.3
Summary: A simple static website generator
Home-page: https://github.com/Tina-otoge/sssimp
Author: Tina
License-File: LICENSE
Requires-Dist: appdirs
Requires-Dist: requests
Requires-Dist: BeautifulSoup4
Requires-Dist: pyyaml
Requires-Dist: simple-term-menu
